jatsgenerator/__init__.py
jatsgenerator/build.py
jatsgenerator/conf.py
jatsgenerator/generate.py
jatsgenerator/utils.py
jatsgenerator-0.20.0.dist-info/LICENSE
jatsgenerator-0.20.0.dist-info/METADATA
jatsgenerator-0.20.0.dist-info/WHEEL
jatsgenerator-0.20.0.dist-info/top_level.txt
jatsgenerator-0.20.0.dist-info/RECORD
