Metadata-Version: 2.1
Name: jatsgenerator
Version: 0.20.0
Summary: JATS XML generator.
Home-page: https://github.com/elifesciences/jats-generator
Maintainer: eLife Sciences Publications Ltd.
Maintainer-email: tech-team@elifesciences.org
License: MIT
Classifier: Development Status :: 3 - Alpha
Classifier: Intended Audience :: Developers
Classifier: License :: OSI Approved :: MIT License
Classifier: Programming Language :: Python :: 3
License-File: LICENSE
Requires-Dist: elifetools >=0.46.0
Requires-Dist: elifearticle >=0.24.0
Requires-Dist: ejpcsvparser >=0.3.0
Requires-Dist: GitPython
Requires-Dist: configparser
